windows_ha_util/Controller.py
windows_ha_util/__init__.py
windows_ha_util/discovery.py
windows_ha_util-0.1.2.dist-info/WHEEL
windows_ha_util-0.1.2.dist-info/METADATA
windows_ha_util-0.1.2.dist-info/RECORD
