Metadata-Version: 2.1
Name: windows-ha-util
Version: 0.1.2
Summary: 
Author: Jacob Clarke
Author-email: jacobclarke718@gmail.com
Requires-Python: >=3.8,<4.0
Classifier: Programming Language :: Python :: 3
Classifier: Programming Language :: Python :: 3.8
Classifier: Programming Language :: Python :: 3.9
Requires-Dist: python-nmap (>=0.6.1,<0.7.0)
Requires-Dist: requests (>=2.25.1,<3.0.0)
